{
    "tag": "example",
    "level": 4,
    "type": "app",
    "parm": "'fun_3_a', skipNames,skipOpen,skipHeader,skipClose",
    "parms": {
        "opt": {
            "1": "fun_3_a"
        },
        "prm": {
            "skipNames": true,
            "skipOpen": true,
            "skipHeader": true,
            "skipClose": true
        }
    },
    "parentID": 7,
    "parentOCC": 6,
    "occurs": {
        "1": {
            "id": 1,
            "type": "start",
            "childs": true,
            "size": 2921
        }
    },
    "childs": true,
    "size": 2921,
    "result": "true",
    "source": "tagResult"
}