{
    "0": "/home/herbert/pad/pad/lib/trace.php:18 - padTraceStack",
    "1": "/home/herbert/pad/pad/lib/error.php:231 - padTrace",
    "2": "/home/herbert/pad/pad/lib/error.php:134 - padErrorReport",
    "3": "/home/herbert/pad/pad/lib/error.php:101 - padErrorTry",
    "4": "/home/herbert/pad/pad/lib/error.php:39 - padErrorGo",
    "5": "/home/herbert/pad/pad/level/type.php:3 - padErrorHandler",
    "6": "/home/herbert/pad/pad/level/level.php:29 - include",
    "7": "/home/herbert/pad/pad/pad.php:4 - include",
    "8": "/home/herbert/pad/www/index.php:39 - include"
}