{
    "tag": "first",
    "t-type": "tag",
    "pair": true,
    "p-type": "none",
    "prm": {
        "0": "",
        "1": ""
    },
    "true": " <tr> {names} <th> {$name} </th> {/names} </tr> ",
    "false": "",
    "base": " <tr> {names} <th> {$name} </th> {/names} </tr> ",
    "html": " <tr> <th> department </th> <th> manager </th> <th> phone </th> </tr> ",
    "result": " <tr> <th> department </th> <th> manager </th> <th> phone </th> </tr> ",
    "name": "first",
    "default": true,
    "walk": "start",
    "hit": true,
    "null": false,
    "else": false,
    "array": false,
    "text": false
}