{
    "tag": "ajax",
    "t-type": "app",
    "pair": false,
    "p-type": "open",
    "prm": {
        "0": "app='reference', page='sequence/step_multiple'",
        "app": "reference",
        "1": "reference",
        "_first_Key_": "app",
        "page": "sequence/step_multiple",
        "2": "sequence/step_multiple"
    },
    "true": "",
    "false": "",
    "base": "",
    "html": "",
    "result": "",
    "name": "",
    "default": true,
    "walk": "start",
    "hit": false,
    "null": false,
    "else": false,
    "array": false,
    "text": false
}